XssRuchongBingdu/README.md
XssRuchongBingdu/__init__.py
XssRuchongBingdu/__main__.py
XssRuchongBingdu/file.epub
XssRuchongBingdu/index.html
XssRuchongBingdu/css/__init__.py
XssRuchongBingdu/css/annotations.css
XssRuchongBingdu/css/main.css
XssRuchongBingdu/css/normalize.css
XssRuchongBingdu/css/popup.css
XssRuchongBingdu/font/__init__.py
XssRuchongBingdu/font/fontello.eot
XssRuchongBingdu/font/fontello.svg
XssRuchongBingdu/font/fontello.ttf
XssRuchongBingdu/font/fontello.woff
XssRuchongBingdu/img/__init__.py
XssRuchongBingdu/img/annotator-glyph-sprite.png
XssRuchongBingdu/img/annotator-icon-sprite.png
XssRuchongBingdu/img/apple-touch-icon.png
XssRuchongBingdu/img/cancelfullscreen.png
XssRuchongBingdu/img/close.png
XssRuchongBingdu/img/fullscreen.png
XssRuchongBingdu/img/loader.gif
XssRuchongBingdu/img/menu-icon.png
XssRuchongBingdu/img/save.png
XssRuchongBingdu/img/saved.png
XssRuchongBingdu/img/settings-s.png
XssRuchongBingdu/img/settings.png
XssRuchongBingdu/img/star.png
XssRuchongBingdu/js/__init__.py
XssRuchongBingdu/js/epub.js
XssRuchongBingdu/js/epub.min.js
XssRuchongBingdu/js/epub.min.map
XssRuchongBingdu/js/hooks.min.js
XssRuchongBingdu/js/hooks.min.map
XssRuchongBingdu/js/reader.js
XssRuchongBingdu/js/reader.js.map
XssRuchongBingdu/js/reader.min.js
XssRuchongBingdu/js/reader.min.map
XssRuchongBingdu/js/hooks/__init__.py
XssRuchongBingdu/js/hooks/extensions/__init__.py
XssRuchongBingdu/js/hooks/extensions/highlight.js
XssRuchongBingdu/js/libs/__init__.py
XssRuchongBingdu/js/libs/jquery.min.js
XssRuchongBingdu/js/libs/localforage.min.js
XssRuchongBingdu/js/libs/screenfull.js
XssRuchongBingdu/js/libs/screenfull.min.js
XssRuchongBingdu/js/libs/zip.min.js
XssRuchongBingdu/js/plugins/__init__.py
XssRuchongBingdu/js/plugins/hypothesis.js
XssRuchongBingdu/js/plugins/search.js
xss_ruchong_bingdu-2024.3.2.0.dist-info/METADATA
xss_ruchong_bingdu-2024.3.2.0.dist-info/WHEEL
xss_ruchong_bingdu-2024.3.2.0.dist-info/entry_points.txt
xss_ruchong_bingdu-2024.3.2.0.dist-info/top_level.txt
xss_ruchong_bingdu-2024.3.2.0.dist-info/RECORD
